crc_itu.py
CRC_ITU-0.3.3.dist-info/LICENSE
CRC_ITU-0.3.3.dist-info/METADATA
CRC_ITU-0.3.3.dist-info/WHEEL
CRC_ITU-0.3.3.dist-info/top_level.txt
CRC_ITU-0.3.3.dist-info/RECORD
